messagehandler/__init__.py
messagehandler/message_handler.py
messagehandler_ifn-0.2.0.dist-info/LICENSE
messagehandler_ifn-0.2.0.dist-info/METADATA
messagehandler_ifn-0.2.0.dist-info/WHEEL
messagehandler_ifn-0.2.0.dist-info/top_level.txt
messagehandler_ifn-0.2.0.dist-info/RECORD
