Metadata-Version: 2.1
Name: messagehandler-ifn
Version: 0.2.0
Summary: messagehandler interface
Home-page: https://github.com/davengeo/messagehandler-ifn.git
Author: David Navarro Alvarez
Author-email: me@davengeo.com
License: UNKNOWN
Platform: UNKNOWN
Classifier: Development Status :: 4 - Beta
Classifier: License :: OSI Approved :: European Union Public Licence 1.2 (EUPL 1.2)
Classifier: Programming Language :: Python :: 3.8
Classifier: Topic :: System :: Systems Administration
License-File: LICENSE
Requires-Dist: kombu
